text_to_sql/__init__.py
text_to_sql/agent.py
text_to_sql/database.py
text_to_sql/tools.py
text_to_sql/prompts/__init__.py
text_to_sql/prompts/prompts.py
text2sql_agent-0.1.1.dist-info/METADATA
text2sql_agent-0.1.1.dist-info/WHEEL
text2sql_agent-0.1.1.dist-info/licenses/LICENSE
text2sql_agent-0.1.1.dist-info/RECORD
