Metadata-Version: 2.4
Name: text2sql-agent
Version: 0.1.1
Summary: A flexible, LLM-agnostic text-to-SQL agent that works with any database
Author-email: Jasmin Patel <jasmin.patel@sourcefuse.com>
Maintainer-email: Jasmin Patel <jasmin.patel@sourcefuse.com>
License: MIT
License-File: LICENSE
Keywords: agent,ai,database,langchain,llm,natural-language,sql,text-to-sql
Classifier: Development Status :: 3 - Alpha
Classifier: Intended Audience :: Developers
Classifier: License :: OSI Approved :: MIT License
Classifier: Operating System :: OS Independent
Classifier: Programming Language :: Python :: 3
Classifier: Programming Language :: Python :: 3.8
Classifier: Programming Language :: Python :: 3.9
Classifier: Programming Language :: Python :: 3.10
Classifier: Programming Language :: Python :: 3.11
Classifier: Programming Language :: Python :: 3.12
Classifier: Programming Language :: Python :: 3.13
Classifier: Topic :: Database
Classifier: Topic :: Scientific/Engineering :: Artificial Intelligence
Classifier: Topic :: Software Development :: Libraries :: Python Modules
Requires-Python: >=3.8
Requires-Dist: langchain-community>=0.0.20
Requires-Dist: langchain-core>=0.1.0
Requires-Dist: langchain>=0.1.0
Requires-Dist: sqlalchemy>=2.0.0
Provides-Extra: all
Requires-Dist: anthropic>=0.18.0; extra == 'all'
Requires-Dist: boto3>=1.28.0; extra == 'all'
Requires-Dist: langchain-anthropic>=0.1.0; extra == 'all'
Requires-Dist: langchain-aws>=0.1.0; extra == 'all'
Requires-Dist: langchain-groq>=0.0.1; extra == 'all'
Requires-Dist: langchain-openai>=0.0.5; extra == 'all'
Requires-Dist: openai>=1.0.0; extra == 'all'
Requires-Dist: psycopg2-binary>=2.9.0; extra == 'all'
Requires-Dist: pymysql>=1.1.0; extra == 'all'
Requires-Dist: pyodbc>=4.0.0; extra == 'all'
Provides-Extra: all-dbs
Requires-Dist: psycopg2-binary>=2.9.0; extra == 'all-dbs'
Requires-Dist: pymysql>=1.1.0; extra == 'all-dbs'
Requires-Dist: pyodbc>=4.0.0; extra == 'all-dbs'
Provides-Extra: all-llms
Requires-Dist: anthropic>=0.18.0; extra == 'all-llms'
Requires-Dist: boto3>=1.28.0; extra == 'all-llms'
Requires-Dist: langchain-anthropic>=0.1.0; extra == 'all-llms'
Requires-Dist: langchain-aws>=0.1.0; extra == 'all-llms'
Requires-Dist: langchain-groq>=0.0.1; extra == 'all-llms'
Requires-Dist: langchain-openai>=0.0.5; extra == 'all-llms'
Requires-Dist: openai>=1.0.0; extra == 'all-llms'
Provides-Extra: anthropic
Requires-Dist: anthropic>=0.18.0; extra == 'anthropic'
Requires-Dist: langchain-anthropic>=0.1.0; extra == 'anthropic'
Provides-Extra: bedrock
Requires-Dist: boto3>=1.28.0; extra == 'bedrock'
Requires-Dist: langchain-aws>=0.1.0; extra == 'bedrock'
Provides-Extra: bigquery
Requires-Dist: sqlalchemy-bigquery>=1.6.0; extra == 'bigquery'
Provides-Extra: dev
Requires-Dist: black>=22.0.0; extra == 'dev'
Requires-Dist: build>=0.10.0; extra == 'dev'
Requires-Dist: flake8>=5.0.0; extra == 'dev'
Requires-Dist: mypy>=1.0.0; extra == 'dev'
Requires-Dist: pytest-asyncio>=0.21.0; extra == 'dev'
Requires-Dist: pytest-html>=4.1.1; extra == 'dev'
Requires-Dist: pytest>=7.0.0; extra == 'dev'
Requires-Dist: twine>=4.0.0; extra == 'dev'
Provides-Extra: google
Requires-Dist: langchain-google-genai>=0.0.5; extra == 'google'
Provides-Extra: groq
Requires-Dist: langchain-groq>=0.0.1; extra == 'groq'
Provides-Extra: mssql
Requires-Dist: pyodbc>=4.0.0; extra == 'mssql'
Provides-Extra: mysql
Requires-Dist: pymysql>=1.1.0; extra == 'mysql'
Provides-Extra: ollama
Requires-Dist: langchain-ollama>=0.0.1; extra == 'ollama'
Provides-Extra: openai
Requires-Dist: langchain-openai>=0.0.5; extra == 'openai'
Requires-Dist: openai>=1.0.0; extra == 'openai'
Provides-Extra: postgresql
Requires-Dist: psycopg2-binary>=2.9.0; extra == 'postgresql'
